Metadata-Version: 2.1
Name: spikes-services-back-lib
Version: 0.0.1
Summary: various tools used for the Spikes algorithms
Home-page: UNKNOWN
Author: Michael Rubinfeld
License: UNKNOWN
Platform: UNKNOWN
